{
    "title": "【鉄道模型】曲線デッキガーダーを使ったジオラマ",
    "keyword": ["鉄道模型", "ジオラマ"],
    "tag": [""],
    "category":"ctg4",
    "summary":"車両展示用に作成した35 cm×60 cmのジオラマの紹介です。",
    "library":[""],
    "article":"
    
    
<h3>はじめに</h3>
<p>
しばらく離れていた鉄道模型ですが、今夏また熱が吹き返しまして、KATOから新発売のJR四国2000系気動車とJR西日本381系電車をポチってしまいました。
どちらも振り子式の特急用車両で、2000系は四国各地のディーゼル特急（「南風」や「うずしお」等）、381系は伯備線を走る「やくも」に充当されています。
どちらも、貫通運転台と非運転台の切妻面が連結するという編成です。わたくし、この「貫通運転台＋非運転台」が大好きなのです。
</p><p>
せっかくですから、これらの車両を飾る展示台となるようなジオラマを作成しようと思い立ちました。これまで、興味を持っていましたが、手を出していなかったKATO製の曲線ガーダーを使うことにしました。
曲線ガーダー橋は、伯備線でよく利用されているので、381系にはピッタリかと思います。ただ、今回は、伯備線色を押さえ、どの車両にもマッチするような汎用的なシーナリー（悪く言えば没個性的？）に仕上げました。
<p></p>
実はまだ細部が完成していないのですが、一区切りついたので載せてしまいます。
</p>


<h3>ジオラマ紹介</h3>
<p>
製作記の前に、早速2000系、381系を展示した様子をご紹介します。R481 のカーブで構成し、20m級車両だと4両編成が収まります。
線路は接続できるようになっているので、お座敷レイアウトに組み込むことも可能です。
（建物の加工や土台側面の処理は後々やる予定です……。）
</p>

<div class='fig'>
<a href='./a21/22.jpg'><img src='./a21/22.jpg' class='fig'></a>
<p class='legend'>
ガーダー橋を渡る2000系。気動車は片側運転台付きの先頭車が連なるので壮観です。
</p></div>

<div class='fig'>
<a href='./a21/23.jpg'><img src='./a21/23.jpg' class='fig'></a>
<p class='legend'>
ちょっと角度を変えて、381系。緑色と灰色がメインのジオラマで、赤いラインが際立ちます。
</p></div>



<h3>ジオラマ製作記</h3>
<h4>線路の配置と固定</h4>
<p>
ジオラマの土台（ホームセンターでベニヤ版を買って加工しました）の上に線路を引いていきます。曲線ガーダー橋2連を中心に考えます。
</p><p>
レールはAKTOユニトラックです。KATO製曲線ガーダーありきのジオラマですし、線路の接続面を加工するのもめんどくさかったので、同じメーカーにしました。
ユニトラックは道床が大きく、枕木と道床部分の差が小さいので、バラストを撒きにくいのではないかという懸念がありましたが、線路両側はそんなに大変ではなく、また、レール間にはバラストを撒かずに済ませました。
</p><p>
ガーダー橋を使うので、レールの高さはベースとなるベニヤ板よりも高くする必要があります。今回は伯備線らしく築堤にします。
築堤のベースは100均で購入したスチロール板を使います。
</p>

<div class='fig'>
<a href='./a21/1.jpg'><img src='./a21/1.jpg' class='fig'></a>
<p class='legend'>
レールの仮置き。
</p></div>

<p>
築堤のイメージが固まったら、橋脚を準備します。真ん中はKATOの標準的な橋脚、築堤の妻面も兼ねる両端の橋脚はプラ板で自作しました。
</p><p>
橋脚は、手元にあった灰色（クレオスの軍艦色（２））で塗った後、タミヤのエナメルブラックでウォッシング後、同じくエナメルのブラウンで強めに錆が流れた様子を表現しました。
</p>

<div class='fig'>
<a href='./a21/2.jpg'><img src='./a21/2.jpg' class='fig'></a>
<p class='legend'>
橋脚の作成と仮置き。
</p></div>

<div class='fig'>
<a href='./a21/3.jpg'><img src='./a21/3.jpg' class='fig'></a>
<p class='legend'>
橋脚の塗装。エナメルブラックでウォッシング後の様子。
</p></div>

<p>
築堤は、仮置きでも使った台形型に切り出したスチロールを並べて骨格を作ったら、その間にキッチンペーパーを詰めて形を作ります。その後、表面にキッチンペーパーをボンドを使ってはり重ねて整形します。
</p>

<div class='fig'>
<a href='./a21/4.jpg'><img src='./a21/4.jpg' class='fig'></a>
<p class='legend'>
築堤の骨格に、キッチンペーパーを詰める。
</p></div>

<div class='fig'>
<a href='./a21/5.jpg'><img src='./a21/5.jpg' class='fig'></a>
<p class='legend'>
表面にキッチンペーパーを張り終えたら築堤はひとまず完成。
</p></div>




<h4>地形の作成</h4>

<p>
周囲の地形はスチロールを積み重ねて大まかな形を作り、細かいところは紙粘土で埋めていきます。紙粘土も100均のものを利用していますが、大きな問題は発生しませんでした。
</p><p>
作成途中では、適宜レールや建物等を付けたり外したりしながら、イメージチェックをしていきます。少し山奥に入った農村のイメージです。水路側面には、グリーンマックスから出ている石垣表現のプラ板も利用しました。
建物はそこまでこだわりと技術がないので、Tomixやジオコレの既製品を利用しました。
</p>

<div class='fig'>
<a href='./a21/7.jpg'><img src='./a21/7.jpg' class='fig'></a>
<p class='legend'>
地形を作る。
</p></div>

<div class='fig'>
<a href='./a21/9.jpg'><img src='./a21/9.jpg' class='fig'></a>
<p class='legend'>
イメージチェックしつつ、細かい部分を仕上げていく。
</p></div>

<p>
農村なので、もちろん畑が必要です。100均のボール紙のうち、最も目が細かいものを利用しました。
</p><p>
地形としてはこれで完成。この後は、塗装ののち、植物を生やしたり、砂利を撒いたりして、表面を仕上げてジオラマらしくしていきます。
</p>

<div class='fig'>
<a href='./a21/10.jpg'><img src='./a21/10.jpg' class='fig'></a>
<p class='legend'>
地形の完成。
</p></div>




<h4>地形の作成</h4>

<p>
缶スプレーで下地の塗装を行います。ホームセンターで売っている適当な茶色のスプレー（つやあり）で塗装しました。
「どうせ下地だし」と思って適当なスプレーを吹き付けましたが、植物として張り付けたスポンジの間から顔を覗かせたり、つやが残ってしまったりと意外と後々効いてきました。
もう少しこだわればよかったなと思っています。
</p>

<div class='fig'>
<a href='./a21/11.jpg'><img src='./a21/11.jpg' class='fig'></a>
<p class='legend'>
地形の下地塗装。
</p></div>

<p>
下地塗装が終わったら、その上から道路・擁壁等コンクリート部分の塗装を行いました。また、砂粒（KATOで販売されているバラスト用のもの）を撒いて砂利道を表現します。
それから、コースターフと呼ばれる緑スポンジの粒（これもKATOから販売されています）
を張り付けていきます。
これで、植物を表現するわけです。
バラスト、コースターフはボンド水（水にボンドを溶いて、中性洗剤1滴を垂らしたもの）で固定します。
</p>

<div class='fig'>
<a href='./a21/12.jpg'><img src='./a21/12.jpg' class='fig'></a>
<p class='legend'>
植物や道路など、地表面を作っていく。白い部分はボンド水。
</p></div>

<p>
ここまで終わるとだいぶジオラマらしくなってきます。
</p><p>
早速、車両を飾ってみます。緑と灰色ばかりだったので、KATO製のガードレールを設置してみたらぐっと引き締まったような気がします。小物は重要ですね！
</p>

<div class='fig'>
<a href='./a21/13.jpg'><img src='./a21/13.jpg' class='fig'></a>
<p class='legend'>
とりあえず、ジオラマっぽくなりました。写っているのはJR四国8000系電車（マイクロエース製）。
</p></div>


<h4>川の表現</h4>

<p>
川の流れを表現します。まず、川の部分を塗装します。最初青と緑で塗ったのですが、あまりに鮮やかになってしまったので、灰色を上に塗って、少し淀んだ感じを表現します。
この川はそんなに深くない設定なので、下床の砂利やコンクリートの色が見えているようなイメージです。
</p>

<div class='fig'>
<a href='./a21/16.jpg'><img src='./a21/16.jpg' class='fig'></a>
<p class='legend'>
川の部分に色を付ける。
</p></div>

<p>
水の表現には、一番手っ取り早いボンドを利用します。ボンドをそのまま、川の色を塗った場所に塗りたくっていきます。波や流れに気を付けるべきですが、今回は適当に塗りました。
</p><p>
乾くと透明になり、それっぽく見えてくるはずです。少なくとも、川なんだなということはわかるでしょう。
</p>

<div class='fig'>
<a href='./a21/17.jpg'><img src='./a21/17.jpg' class='fig'></a>
<p class='legend'>
川の水の表現にはボンドを利用。塗りたくる。
</p></div>

<div class='fig'>
<a href='./a21/18.jpg'><img src='./a21/18.jpg' class='fig'></a>
<p class='legend'>
ボンドが乾くと透明な膜となり、水っぽく見える……はずです。
</p></div>




<h4>木を植えてひとまず完成!?</h4>

<p>
レールと建物を設置してだいぶ完成に近づきました。ただ、少し寂しいので、木を植えて立体感を出していきましょう。
</p>

<div class='fig'>
<a href='./a21/19.jpg'><img src='./a21/19.jpg' class='fig'></a>
<p class='legend'>
完成間近!?　線路にバラスト（Tomix製）を撒き、架線柱も付けたが、樹木がないと物足りない。
</p></div>

<p>
まず、木の幹を作ります。銅線をより合わせて枝ぶりを作った後、針金感を誤魔化すためティッシュを撒きつけて、茶色で塗装しました。かなり大雑把です。
</p>

<div class='fig'>
<a href='./a21/20.jpg'><img src='./a21/20.jpg' class='fig'></a>
<p class='legend'>
銅線をより合わせて樹木の幹・枝を作る。
</p></div>

<p>
塗装が乾いたら、枝にボンドを付けて、緑のスポンジのかたまり（フォーリッジクラスターという名前でKATOから販売されています）をちぎってくっつけていきます。
ボンドが乾いてフォーリッジクラスターが固着したら、ジオラマに穴を開けて、差し込んでいきます。
</p>

<div class='fig'>
<a href='./a21/21.jpg'><img src='./a21/21.jpg' class='fig'></a>
<p class='legend'>
銅線で作った枝にフォリッジクラスターを固着させ、葉を作る。
</p></div>

<p>
これにていったんジオラマは完成です。
個人的な考えとして、コースターフやフォーリッジクラスターをケチらずにたっぷり使うことがそれっぽく見せられるコツなのかなぁと思います。
</p><p>
本当は、建物の塗装を変更したり、ジオラマベースの側面処理したり（今はスチロールがむき出し(-_-;)）とやってみたいことはあるのですが、とりあえず自己満足できる領域になったので、これで一段落とします。
また、修正したらこの記事も更新したいと思います。
</p>

<div class='fig'>
<a href='./a21/25.jpg'><img src='./a21/25.jpg' class='fig'></a>
<p class='legend'>
これでひとまず完成。樹木を植えたことで、密度感と立体感が生まれたと思う。
</p></div>


    ",
    "history":["2019年10月1日公開"]
}